nanonis_spm_specs/NanonisClass.py
nanonis_spm_specs/__init__.py
nanonis_spm_specs-0.0.5.dist-info/METADATA
nanonis_spm_specs-0.0.5.dist-info/WHEEL
nanonis_spm_specs-0.0.5.dist-info/licenses/LICENSE.txt
nanonis_spm_specs-0.0.5.dist-info/RECORD
