Metadata-Version: 2.3
Name: nanonis_spm_specs
Version: 0.0.5
Summary: Python package for controlling Nanonis SPM software through python
Author-email: Samuel O'Neill <samuel.oneill@specs-zurich.com>
License-File: LICENSE.txt
Classifier: Operating System :: OS Independent
Classifier: Programming Language :: Python :: 3
Requires-Python: >=3.8
